{
  "project_info": {
    "project_number": "1034420099525",
    "project_id": "fitness-app-db5da",
    "storage_bucket": "fitness-app-db5da.firebasestorage.app"
  },
  "client": [
    {
      "client_info": {
        "mobilesdk_app_id": "1:1034420099525:android:fe1a158e33cbf0c8cb93ac",
        "android_client_info": {
          "package_name": "com.example.ryan"
        }
      },
      "oauth_client": [],
      "api_key": [
        {
          "current_key": "AIzaSyCMbqKUQVWkjCNW5GfQLv2Yid3bVdxBjuo"
        }
      ],
      "services": {
        "appinvite_service": {
          "other_platform_oauth_client": []
        }
      }
    }
  ],
  "configuration_version": "1"
}